meshpy/__init__.py
meshpy/_internals.cp39-win_amd64.pyd
meshpy/common.py
meshpy/geometry.py
meshpy/gmsh.py
meshpy/gmsh_reader.py
meshpy/naca.py
meshpy/ply.py
meshpy/tet.py
meshpy/tools.py
meshpy/triangle.py
MeshPy-2022.1.3.dist-info/LICENSE
MeshPy-2022.1.3.dist-info/METADATA
MeshPy-2022.1.3.dist-info/WHEEL
MeshPy-2022.1.3.dist-info/top_level.txt
MeshPy-2022.1.3.dist-info/RECORD
