Metadata-Version: 2.1
Name: MeshPy
Version: 2022.1.3
Summary: Triangular and Tetrahedral Mesh Generator
Home-page: https://documen.tician.de/meshpy
Author: Andreas Kloeckner
Author-email: inform@tiker.net
License: MIT for the wrapper/non-commercial for the Triangle/GNU Affero Public License for TetGen
Platform: UNKNOWN
Classifier: Development Status :: 4 - Beta
Classifier: Intended Audience :: Developers
Classifier: Intended Audience :: Other Audience
Classifier: Intended Audience :: Science/Research
Classifier: License :: OSI Approved :: MIT License
Classifier: License :: Free for non-commercial use
Classifier: Natural Language :: English
Classifier: Programming Language :: C++
Classifier: Programming Language :: Python
Classifier: Programming Language :: Python :: 3
Classifier: Topic :: Multimedia :: Graphics :: 3D Modeling
Classifier: Topic :: Scientific/Engineering
Classifier: Topic :: Scientific/Engineering :: Mathematics
Classifier: Topic :: Scientific/Engineering :: Physics
Classifier: Topic :: Scientific/Engineering :: Visualization
Classifier: Topic :: Software Development :: Libraries
Requires-Python: ~=3.6
License-File: LICENSE
Requires-Dist: pytools (>=2011.2)
Requires-Dist: numpy
Requires-Dist: gmsh-interop
